vmongodb/__init__.py
vmongodb/IncrementalDataBase.py
vmongodb/operations.py
vmongodb-0.1.2.dist-info/WHEEL
vmongodb-0.1.2.dist-info/METADATA
vmongodb-0.1.2.dist-info/RECORD
